MyLogColor.py
mylogcolor-0.0.2.dist-info/METADATA
mylogcolor-0.0.2.dist-info/WHEEL
mylogcolor-0.0.2.dist-info/licenses/LICENSE
mylogcolor-0.0.2.dist-info/RECORD
