Metadata-Version: 2.1
Name: MyLogColor
Version: 0.0.2
Summary: This is a python package that uses the rough set algorithm to measure which features can be reduced.
Project-URL: Homepage, https://github.com/YiyaoZhang9527
Author-email: ManmanZhang <408903228@qq.com>
License: MIT License
License-File: LICENSE
Classifier: License :: OSI Approved :: MIT License
Classifier: Operating System :: OS Independent
Classifier: Programming Language :: Python :: 3
Requires-Python: >=3.7
